wavedrom_ascii/__init__.py
wavedrom_ascii-0.2.1.dist-info/LICENSE
wavedrom_ascii-0.2.1.dist-info/WHEEL
wavedrom_ascii-0.2.1.dist-info/METADATA
wavedrom_ascii-0.2.1.dist-info/RECORD
