Metadata-Version: 2.1
Name: wavedrom-ascii
Version: 0.2.1
Summary: Wavedrom waves and registers for the terminal
Home-page: https://github.com/zegervdv/wavedrom-ascii
License: MIT
Author: zegervdv
Author-email: zegervdv@me.com
Requires-Python: >=3.5,<4.0
Classifier: License :: OSI Approved :: MIT License
Classifier: Programming Language :: Python :: 3
Classifier: Programming Language :: Python :: 3.5
Classifier: Programming Language :: Python :: 3.6
Classifier: Programming Language :: Python :: 3.7
Classifier: Programming Language :: Python :: 3.8
Classifier: Programming Language :: Python :: 3.9
Requires-Dist: json5 (>=0.9.5,<0.10.0)
Project-URL: Repository, https://github.com/zegervdv/wavedrom-ascii
